nb_even_booth.v
`timescale 1ns/1ns

module nb_even_booth(clk, start, A, B, PP_Result_Multiplier, ready);

//-----------------------Port directions and deceleration
   parameter nb = 12;

   input clk;
   input start;
   input signed [nb - 1 : 0] A;
   input signed [nb  - 1 : 0] B; 
   output reg [2 * nb - 1 : 0] PP_Result_Multiplier;
   output ready;


//------------------------------------------------------

//----------------------------------- register deceleration

reg prev_bit;
reg signed [nb - 1 : 0] Multiplicand;
reg [$clog2(nb) / 2 : 0]  counter; //am i right?!

//-------------------------------------------------------

//------------------------------------- wire deceleration

reg signed [nb+1 : 0] adder_output;
wire signed [nb : 0] negated_A;
wire signed [nb + 1 : 0] negated_2A;
wire signed [nb + 1 : 0] positive_2A;

//---------------------------------------------------------

//-------------------------------------- combinational logic

assign ready = (counter == nb / 2);
assign negated_A = ~Multiplicand + 1;
assign negated_2A = ~(Multiplicand << 1) + 1;
assign positive_2A = Multiplicand << 1;

//---------------------------------------------------------

always @(*) begin
    if(PP_Result_Multiplier[1:0] == 2'b00) begin
            if(prev_bit == 1'b0) //0
                adder_output <= {PP_Result_Multiplier[2*nb - 1], PP_Result_Multiplier[2*nb - 1], PP_Result_Multiplier[2*nb - 1 : nb]};
            else //A
                adder_output <= {PP_Result_Multiplier[2*nb - 1], PP_Result_Multiplier[2*nb - 1], PP_Result_Multiplier[2*nb - 1 : nb]} + {Multiplicand[nb - 1], Multiplicand[nb - 1], Multiplicand};
      end
      else if(PP_Result_Multiplier[1:0] == 2'b01) begin
            if(prev_bit == 1'b0) //A
                adder_output <= {PP_Result_Multiplier[2*nb - 1], PP_Result_Multiplier[2*nb - 1], PP_Result_Multiplier[2 * nb - 1 : nb]} + {Multiplicand[nb - 1], Multiplicand[nb - 1], Multiplicand};
            else //2A
                adder_output <= {PP_Result_Multiplier[2 * nb - 1], PP_Result_Multiplier[2 * nb - 1], PP_Result_Multiplier[2*nb - 1 : nb]} + {positive_2A};
      end
      else if(PP_Result_Multiplier[1:0] == 2'b10) begin
            if(prev_bit == 1'b0) //-2A
                adder_output <= {PP_Result_Multiplier[2 * nb - 1], PP_Result_Multiplier[2*nb - 1], PP_Result_Multiplier[2*nb - 1 : nb]} + {negated_2A};
            else //-A
                adder_output <= {PP_Result_Multiplier[2*nb - 1], PP_Result_Multiplier[2*nb - 1], PP_Result_Multiplier[2*nb - 1 : nb]} + {negated_A[nb - 1], negated_A};
      end
      //else if(PP_Result_Multiplier[1:0] == 2'b11) begin
      else begin  
            if(prev_bit == 1'b0) //-A
                adder_output <= {PP_Result_Multiplier[2*nb - 1], PP_Result_Multiplier[2*nb - 1], PP_Result_Multiplier[2*nb - 1 : nb]} + {negated_A[nb - 1], negated_A};
            else //0
                adder_output <= {PP_Result_Multiplier[2*nb - 1], PP_Result_Multiplier[2*nb - 1], PP_Result_Multiplier[2*nb - 1 : nb]};
      end
end

//--------------------------------------- sequential Logic

always @ (posedge clk)

   if(start) begin
      prev_bit <= 0;
      counter <= 0;
      //Multiplier <= B;
      Multiplicand <= A;
      PP_Result_Multiplier <= {8'h00, B};
    end

   else if(!ready) begin

      counter <= counter + 1;
      prev_bit <= PP_Result_Multiplier[1];
      PP_Result_Multiplier <= {adder_output, PP_Result_Multiplier[nb - 1 : 2]};
   end 
endmodule

nb_even_booth_tb.v

`timescale 1ns/1ns

module nb_even_booth_tb();

   parameter no_of_tests = 100;
   parameter nb = 12;

//------------------generating clock signal in 100MHz
   reg clk = 1'b1;
   always @(clk)
      clk <= #5 ~clk;
//-----------------------------------------------------
 
//-------------------------------------- reg declaration 
   reg start;
   reg signed [(nb -1) : 0] A, B, C, D;
   reg signed [(2*nb -1) : 0] expected_product;
//----------------------------------------------------------    
   integer i, j, err = 0;

   initial begin
      $dumpfile("waveform.vcd");
      $dumpvars(0, nb_even_booth_tb);
   end
   
   initial begin
      start = 0;

      @(posedge clk);
      @(posedge clk);
      @(posedge clk);
      #1;
//------------------------------------------repeat the test no_of_tests times with different random numbers
      for(i=0; i<no_of_tests; i=i+1) begin

         A = $random();    
         B = $random();
         expected_product = A * B;
         C = A;
         D = B;
      //----------------------------------generating start signal -------------------------------------------------------------     
         start = 1;
         @(posedge clk);
         #1;
         start = 0;
         A = 'bx; //When start became "1" we register A & B and their changes is not important after start became "0"
         B = 'bx; //When start became "1" we register A & B and their changes is not important after start became "0"
      //----------------------------------------------------------------------------------------------------------------------
         
      //-----------------------------------wait until multiplication become complete
         for(j=0; j<=nb; j=j+1)        
            @(posedge clk);
         @(posedge clk);
      //------------------------------------------------------------------------------

         $write   ("%x (%0d) x %x (%0d) = %x (%0d) ", C, C, D, D, uut.PP_Result_Multiplier, $signed(uut.PP_Result_Multiplier));

         if (expected_product === uut.PP_Result_Multiplier)
            $display(", OK");
         else 
            $display (", ERROR: expected %x, got %x", expected_product, uut.PP_Result_Multiplier); 

      end

      $stop;
   end


    nb_even_booth uut (
        .clk(clk),
        .start(start),
        .A(A),
        .B(B),
        .PP_Result_Multiplier(),
        .ready()
    );


endmodule

waveform.vcd
$date
	Sat Jun 20 19:23:21 2026
$end
$version
	ModelSim Version 2020.4
$end
$timescale
	1ns
$end

$scope module nb_even_booth_tb $end
$var parameter 32 ! no_of_tests $end
$var parameter 32 " nb $end
$var reg 1 # clk $end
$var reg 1 $ start $end
$var reg 12 % A [11:0] $end
$var reg 12 & B [11:0] $end
$var reg 12 ' C [11:0] $end
$var reg 12 ( D [11:0] $end
$var reg 24 ) expected_product [23:0] $end
$var integer 32 * i $end
$var integer 32 + j $end
$var integer 32 , err $end

$scope module uut $end
$var parameter 32 - nb $end
$var wire 1 . clk $end
$var wire 1 / start $end
$var wire 1 0 A [11] $end
$var wire 1 1 A [10] $end
$var wire 1 2 A [9] $end
$var wire 1 3 A [8] $end
$var wire 1 4 A [7] $end
$var wire 1 5 A [6] $end
$var wire 1 6 A [5] $end
$var wire 1 7 A [4] $end
$var wire 1 8 A [3] $end
$var wire 1 9 A [2] $end
$var wire 1 : A [1] $end
$var wire 1 ; A [0] $end
$var wire 1 < B [11] $end
$var wire 1 = B [10] $end
$var wire 1 > B [9] $end
$var wire 1 ? B [8] $end
$var wire 1 @ B [7] $end
$var wire 1 A B [6] $end
$var wire 1 B B [5] $end
$var wire 1 C B [4] $end
$var wire 1 D B [3] $end
$var wire 1 E B [2] $end
$var wire 1 F B [1] $end
$var wire 1 G B [0] $end
$var reg 24 H PP_Result_Multiplier [23:0] $end
$var wire 1 I ready $end
$var reg 1 J prev_bit $end
$var reg 12 K Multiplicand [11:0] $end
$var reg 3 L counter [2:0] $end
$var reg 14 M adder_output [13:0] $end
$var wire 1 N negated_A [12] $end
$var wire 1 O negated_A [11] $end
$var wire 1 P negated_A [10] $end
$var wire 1 Q negated_A [9] $end
$var wire 1 R negated_A [8] $end
$var wire 1 S negated_A [7] $end
$var wire 1 T negated_A [6] $end
$var wire 1 U negated_A [5] $end
$var wire 1 V negated_A [4] $end
$var wire 1 W negated_A [3] $end
$var wire 1 X negated_A [2] $end
$var wire 1 Y negated_A [1] $end
$var wire 1 Z negated_A [0] $end
$var wire 1 [ negated_2A [13] $end
$var wire 1 \ negated_2A [12] $end
$var wire 1 ] negated_2A [11] $end
$var wire 1 ^ negated_2A [10] $end
$var wire 1 _ negated_2A [9] $end
$var wire 1 ` negated_2A [8] $end
$var wire 1 a negated_2A [7] $end
$var wire 1 b negated_2A [6] $end
$var wire 1 c negated_2A [5] $end
$var wire 1 d negated_2A [4] $end
$var wire 1 e negated_2A [3] $end
$var wire 1 f negated_2A [2] $end
$var wire 1 g negated_2A [1] $end
$var wire 1 h negated_2A [0] $end
$var wire 1 i positive_2A [13] $end
$var wire 1 j positive_2A [12] $end
$var wire 1 k positive_2A [11] $end
$var wire 1 l positive_2A [10] $end
$var wire 1 m positive_2A [9] $end
$var wire 1 n positive_2A [8] $end
$var wire 1 o positive_2A [7] $end
$var wire 1 p positive_2A [6] $end
$var wire 1 q positive_2A [5] $end
$var wire 1 r positive_2A [4] $end
$var wire 1 s positive_2A [3] $end
$var wire 1 t positive_2A [2] $end
$var wire 1 u positive_2A [1] $end
$var wire 1 v positive_2A [0] $end
$upscope $end
$upscope $end
$enddefinitions $end
#0
$dumpvars
1#
0$
bx %
bx &
bx '
bx (
bx )
bx H
xJ
bx K
bx L
bx M
b1100100 !
b1100 "
b1100 -
bx *
bx +
b0 ,
xZ
xY
xX
xW
xV
xU
xT
xS
xR
xQ
xP
xO
xN
xh
xg
xf
xe
xd
xc
xb
xa
x`
x_
x^
x]
x\
x[
0v
xu
xt
xs
xr
xq
xp
xo
xn
xm
xl
xk
xj
xi
xG
xF
xE
xD
xC
xB
xA
x@
x?
x>
x=
x<
x;
x:
x9
x8
x7
x6
x5
x4
x3
x2
x1
x0
0/
1.
xI
$end
#5
0#
0.
#10
1#
1.
#15
0#
0.
#20
1#
1.
#25
0#
0.
#30
1#
1.
#31
b0 *
b10100100100 %
b111010000001 &
b111110000100111100100100 )
b10100100100 '
b111010000001 (
1$
1G
0F
0E
0D
0C
0B
0A
1@
0?
1>
1=
1<
0;
0:
19
08
07
16
05
04
13
02
11
00
1/
#35
0#
0.
#40
1#
1.
0J
b0 L
b10100100100 K
b111010000001 H
0I
0Z
0Y
1X
1W
1V
0U
1T
1S
0R
1Q
0P
1O
1N
0h
0g
0f
1e
1d
1c
0b
1a
1`
0_
1^
0]
1\
1[
0u
0t
1s
0r
0q
1p
0o
0n
1m
0l
1k
0j
0i
b10100100100 M
#41
0$
bx %
bx &
b0 +
0/
xG
xF
xE
xD
xC
xB
xA
x@
x?
x>
x=
x<
x;
x:
x9
x8
x7
x6
x5
x4
x3
x2
x1
x0
#45
0#
0.
#50
1#
1.
b1 +
b1 L
b101001001001110100000 H
b101001001 M
#55
0#
0.
#60
1#
1.
b10 +
b10 L
b1010010010011101000 H
b1010010 M
#65
0#
0.
#70
1#
1.
b11 +
b11 L
b10100100100111010 H
b11010111001100 M
#75
0#
0.
#80
1#
1.
b100 +
b100 L
1J
b110101110011001001001110 H
b11100001001111 M
#85
0#
0.
#90
1#
1.
b101 +
b101 L
b111000010011110010010011 H
b11111000010011 M
#95
0#
0.
#100
1#
1.
b110 +
b110 L
b111110000100111100100100 H
1I
b10010101000 M
#105
0#
0.
#110
1#
1.
b111 +
#115
0#
0.
#120
1#
1.
b1000 +
#125
0#
0.
#130
1#
1.
b1001 +
#135
0#
0.
#140
1#
1.
b1010 +
#145
0#
0.
#150
1#
1.
b1011 +
#155
0#
0.
#160
1#
1.
b1100 +
#165
0#
0.
#170
1#
1.
b1101 +
#175
0#
0.
#180
1#
1.
b1 *
b11000001001 %
b11001100011 &
b1001101000101101111011 )
b11000001001 '
b11001100011 (
1$
1G
1F
0E
0D
0C
1B
1A
0@
0?
1>
1=
0<
1;
0:
09
18
07
06
05
04
03
12
11
00
1/
#185
0#
0.
#190
1#
1.
0J
b0 L
b11000001001 K
b11001100011 H
0I
1Z
1Y
0W
1U
1R
0Q
1g
1f
0d
1b
1_
0^
1u
0s
1r
0p
0m
1l
b11100111110111 M
#191
0$
bx %
bx &
b0 +
0/
xG
xF
xE
xD
xC
xB
xA
x@
x?
x>
x=
x<
x;
x:
x9
x8
x7
x6
x5
x4
x3
x2
x1
x0
#195
0#
0.
#200
1#
1.
b1 +
b1 L
1J
b111001111101110110011000 H
b10010000110 M
#205
0#
0.
#210
1#
1.
b10 +
b10 L
0J
b100100001101101100110 H
b11010100001111 M
#215
0#
0.
#220
1#
1.
b11 +
b11 L
1J
b110101000011111011011001 H
b100101010101 M
#225
0#
0.
#230
1#
1.
b100 +
b100 L
0J
b1001010101011110110110 H
b11011001000011 M
#235
0#
0.
#240
1#
1.
b101 +
b101 L
1J
b110110010000110111101101 H
b100110100010 M
#245
0#
0.
#250
1#
1.
b110 +
b110 L
0J
b1001101000101101111011 H
1I
b11110001011111 M
#255
0#
0.
#260
1#
1.
b111 +
#265
0#
0.
#270
1#
1.
b1000 +
#275
0#
0.
#280
1#
1.
b1001 +
#285
0#
0.
#290
1#
1.
b1010 +
#295
0#
0.
#300
1#
1.
b1011 +
#305
0#
0.
#310
1#
1.
b1100 +
#315
0#
0.
#320
1#
1.
b1101 +
#325
0#
0.
#330
1#
1.
b10 *
b101100001101 %
b100110001101 &
b111111110101100101001 )
b101100001101 '
b100110001101 (
1$
1G
0F
1E
1D
0C
0B
0A
1@
1?
0>
0=
1<
1;
0:
19
18
07
06
05
04
13
12
01
10
1/
#335
0#
0.
#340
1#
1.
b0 L
b101100001101 K
b100110001101 H
0I
0X
0R
1P
0O
0N
0e
0_
1]
0\
0[
1s
1m
0k
1j
1i
b11101100001101 M
#341
0$
bx %
bx &
b0 +
0/
xG
xF
xE
xD
xC
xB
xA
x@
x?
x>
x=
x<
x;
x:
x9
x8
x7
x6
x5
x4
x3
x2
x1
x0
#345
0#
0.
#350
1#
1.
b1 +
b1 L
b111011000011011001100011 H
b1110110110 M
#355
0#
0.
#360
1#
1.
b10 +
b10 L
1J
b11101101100110011000 H
b11101111111010 M
#365
0#
0.
#370
1#
1.
b11 +
b11 L
0J
b111011111110101001100110 H
b100011100100 M
#375
0#
0.
#380
1#
1.
b100 +
b100 L
1J
b1000111001001010011001 H
b11100001010011 M
#385
0#
0.
#390
1#
1.
b101 +
b101 L
0J
b111000010100110010100110 H
b11111111010 M
#395
0#
0.
#400
1#
1.
b110 +
b110 L
1J
b111111110101100101001 H
1I
b11100000011000 M
#405
0#
0.
#410
1#
1.
b111 +
#415
0#
0.
#420
1#
1.
b1000 +
#425
0#
0.
#430
1#
1.
b1001 +
#435
0#
0.
#440
1#
1.
b1010 +
#445
0#
0.
#450
1#
1.
b1011 +
#455
0#
0.
#460
1#
1.
b1100 +
#465
0#
0.
#470
1#
1.
b1101 +
#475
0#
0.
#480
1#
1.
b11 *
b10001100101 %
b1000010010 &
b10010001100100011010 )
b10001100101 '
b1000010010 (
1$
0G
1F
0E
0D
1C
0B
0A
0@
0?
1>
0=
0<
1;
0:
19
08
07
16
15
04
03
02
11
00
1/
#485
0#
0.
#490
1#
1.
0J
b0 L
b10001100101 K
b1000010010 H
0I
1W
0U
0T
1R
1Q
0P
1O
1N
1d
0b
0a
1_
1^
0]
1\
1[
0r
1p
1o
0m
0l
1k
0j
0i
b11011100110110 M
#491
0$
bx %
bx &
b0 +
0/
xG
xF
xE
xD
xC
xB
xA
x@
x?
x>
x=
x<
x;
x:
x9
x8
x7
x6
x5
x4
x3
x2
x1
x0
#495
0#
0.
#500
1#
1.
b1 +
b1 L
1J
b110111001101100010000100 H
b1000110010 M
#505
0#
0.
#510
1#
1.
b10 +
b10 L
0J
b10001100101000100001 H
b10011110001 M
#515
0#
0.
#520
1#
1.
b11 +
b11 L
b100111100011010001000 H
b100111100 M
#525
0#
0.
#530
1#
1.
b100 +
b100 L
b1001111000110100010 H
b11011110000101 M
#535
0#
0.
#540
1#
1.
b101 +
b101 L
1J
b110111100001010001101000 H
b1001000110 M
#545
0#
0.
#550
1#
1.
b110 +
b110 L
0J
b10010001100100011010 H
1I
b11011111000111 M
#555
0#
0.
#560
1#
1.
b111 +
#565
0#
0.
#570
1#
1.
b1000 +
#575
0#
0.
#580
1#
1.
b1001 +
#585
0#
0.
#590
1#
1.
b1010 +
#595
0#
0.
#600
1#
1.
b1011 +
#605
0#
0.
#610
1#
1.
b1100 +
#615
0#
0.
#620
1#
1.
b1101 +
#625
0#
0.
#630
1#
1.
b100 *
b1100000001 %
b110100001101 &
b111101110010010000001101 )
b1100000001 '
b110100001101 (
1$
1G
0F
1E
1D
0C
0B
0A
0@
1?
0>
1=
1<
1;
0:
09
08
07
06
05
04
13
12
01
00
1/
#635
0#
0.
#640
1#
1.
b0 L
b1100000001 K
b110100001101 H
0I
1X
1U
1T
0R
0Q
1P
1e
1b
1a
0_
0^
1]
0s
0p
0o
1m
1l
0k
b1100000001 M
#641
0$
bx %
bx &
b0 +
0/
xG
xF
xE
xD
xC
xB
xA
x@
x?
x>
x=
x<
x;
x:
x9
x8
x7
x6
x5
x4
x3
x2
x1
x0
#645
0#
0.
#650
1#
1.
b1 +
b1 L
b11000000011101000011 H
b11110110111111 M
#655
0#
0.
#660
1#
1.
b10 +
b10 L
1J
b111101101111110111010000 H
b1001110000 M
#665
0#
0.
#670
1#
1.
b11 +
b11 L
0J
b10011100001101110100 H
b10011100 M
#675
0#
0.
#680
1#
1.
b100 +
b100 L
b100111000011011101 H
b1100101000 M
#685
0#
0.
#690
1#
1.
b101 +
b101 L
b11001010000000110111 H
b11110111001001 M
#695
0#
0.
#700
1#
1.
b110 +
b110 L
1J
b111101110010010000001101 H
1I
b10101110100 M
#705
0#
0.
#710
1#
1.
b111 +
#715
0#
0.
#720
1#
1.
b1000 +
#725
0#
0.
#730
1#
1.
b1001 +
#735
0#
0.
#740
1#
1.
b1010 +
#745
0#
0.
#750
1#
1.
b1011 +
#755
0#
0.
#760
1#
1.
b1100 +
#765
0#
0.
#770
1#
1.
b1101 +
#775
0#
0.
#780
1#
1.
b101 *
b101110110 %
b110100111101 &
b111110111111011100011110 )
b101110110 '
b110100111101 (
1$
1G
0F
1E
1D
1C
1B
0A
0@
1?
0>
1=
1<
0;
1:
19
08
17
16
15
04
13
02
01
00
1/
#785
0#
0.
#790
1#
1.
0J
b0 L
b101110110 K
b110100111101 H
0I
0Z
0X
0V
0U
0T
1Q
0g
0e
0c
0b
0a
1^
0u
1t
1s
1q
1p
1o
0l
b101110110 M
#791
0$
bx %
bx &
b0 +
0/
xG
xF
xE
xD
xC
xB
xA
x@
x?
x>
x=
x<
x;
x:
x9
x8
x7
x6
x5
x4
x3
x2
x1
x0
#795
0#
0.
#800
1#
1.
b1 +
b1 L
b1011101101101001111 H
b11111011100111 M
#805
0#
0.
#810
1#
1.
b10 +
b10 L
1J
b111110111001111011010011 H
b11111110111001 M
#815
0#
0.
#820
1#
1.
b11 +
b11 L
b111111101110011110110100 H
b101100100 M
#825
0#
0.
#830
1#
1.
b100 +
b100 L
0J
b1011001000111101101 H
b111001111 M
#835
0#
0.
#840
1#
1.
b101 +
b101 L
b1110011110001111011 H
b11111011111101 M
#845
0#
0.
#850
1#
1.
b110 +
b110 L
1J
b111110111111011100011110 H
1I
b11111001001001 M
#855
0#
0.
#860
1#
1.
b111 +
#865
0#
0.
#870
1#
1.
b1000 +
#875
0#
0.
#880
1#
1.
b1001 +
#885
0#
0.
#890
1#
1.
b1010 +
#895
0#
0.
#900
1#
1.
b1011 +
#905
0#
0.
#910
1#
1.
b1100 +
#915
0#
0.
#920
1#
1.
b1101 +
#925
0#
0.
#930
1#
1.
b110 *
b11111101101 %
b11110001100 &
b1110111101000010011100 )
b11111101101 '
b11110001100 (
1$
0G
0F
1E
1D
0C
0B
0A
1@
1?
1>
1=
0<
1;
0:
19
18
07
16
15
14
13
12
11
00
1/
#935
0#
0.
#940
1#
1.
0J
b0 L
b11111101101 K
b11110001100 H
0I
1Z
0W
1V
0S
0Q
0P
1g
0d
1c
0`
0^
0]
1u
0t
1r
0q
1n
1l
1k
b0 M
#941
0$
bx %
bx &
b0 +
0/
xG
xF
xE
xD
xC
xB
xA
x@
x?
x>
x=
x<
x;
x:
x9
x8
x7
x6
x5
x4
x3
x2
x1
x0
#945
0#
0.
#950
1#
1.
b1 +
b1 L
b111100011 H
b11100000010011 M
#955
0#
0.
#960
1#
1.
b10 +
b10 L
1J
b111000000100110001111000 H
b10111110001 M
#965
0#
0.
#970
1#
1.
b11 +
b11 L
0J
b101111100011100011110 H
b11000110100010 M
#975
0#
0.
#980
1#
1.
b100 +
b100 L
1J
b110001101000100111000111 H
b11110001101000 M
#985
0#
0.
#990
1#
1.
b101 +
b101 L
b111100011010001001110001 H
b111011110100 M
#995
0#
0.
#1000
1#
1.
b110 +
b110 L
0J
b1110111101000010011100 H
1I
b1110111101 M
#1005
0#
0.
#1010
1#
1.
b111 +
#1015
0#
0.
#1020
1#
1.
b1000 +
#1025
0#
0.
#1030
1#
1.
b1001 +
#1035
0#
0.
#1040
1#
1.
b1010 +
#1045
0#
0.
#1050
1#
1.
b1011 +
#1055
0#
0.
#1060
1#
1.
b1100 +
#1065
0#
0.
#1070
1#
1.
b1101 +
#1075
0#
0.
#1080
1#
1.
b111 *
b100111111001 %
b10011000110 &
b111000110011101010010110 )
b100111111001 '
b10011000110 (
1$
0G
1F
1E
0D
0C
0B
1A
1@
0?
0>
1=
0<
1;
0:
09
18
17
16
15
14
13
02
01
10
1/
#1085
0#
0.
#1090
1#
1.
b0 L
b100111111001 K
b10011000110 H
0I
1X
0V
1Q
1P
0O
0N
1e
0c
1^
1]
0\
0[
0s
1q
0l
0k
1j
1i
b110000001110 M
#1091
0$
bx %
bx &
b0 +
0/
xG
xF
xE
xD
xC
xB
xA
x@
x?
x>
x=
x<
x;
x:
x9
x8
x7
x6
x5
x4
x3
x2
x1
x0
#1095
0#
0.
#1100
1#
1.
b1 +
b1 L
1J
b1100000011100100110001 H
b11011011110101 M
#1105
0#
0.
#1110
1#
1.
b10 +
b10 L
0J
b110110111101011001001100 H
b11110110111101 M
#1115
0#
0.
#1120
1#
1.
b11 +
b11 L
b111101101111010110010011 H
b10101110110 M
#1125
0#
0.
#1130
1#
1.
b100 +
b100 L
1J
b101011101100101100100 H
b11101101010110 M
#1135
0#
0.
#1140
1#
1.
b101 +
b101 L
0J
b111011010101101001011001 H
b11100011001110 M
#1145
0#
0.
#1150
1#
1.
b110 +
b110 L
b111000110011101010010110 H
1I
b101001000001 M
#1155
0#
0.
#1160
1#
1.
b111 +
#1165
0#
0.
#1170
1#
1.
b1000 +
#1175
0#
0.
#1180
1#
1.
b1001 +
#1185
0#
0.
#1190
1#
1.
b1010 +
#1195
0#
0.
#1200
1#
1.
b1011 +
#1205
0#
0.
#1210
1#
1.
b1100 +
#1215
0#
0.
#1220
1#
1.
b1101 +
#1225
0#
0.
#1230
1#
1.
b1000 *
b10011000101 %
b1010101010 &
b11001011010011010010 )
b10011000101 '
b1010101010 (
1$
0G
1F
0E
1D
0C
1B
0A
1@
0?
1>
0=
0<
1;
0:
19
08
07
06
15
14
03
02
11
00
1/
#1235
0#
0.
#1240
1#
1.
b0 L
b10011000101 K
b1010101010 H
0I
0X
1W
1V
1U
1R
0P
1O
1N
0e
1d
1c
1b
1_
0]
1\
1[
1s
0r
0q
0p
0m
1k
0j
0i
b11011001110110 M
#1241
0$
bx %
bx &
b0 +
0/
xG
xF
xE
xD
xC
xB
xA
x@
x?
x>
x=
x<
x;
x:
x9
x8
x7
x6
x5
x4
x3
x2
x1
x0
#1245
0#
0.
#1250
1#
1.
b1 +
b1 L
1J
b110110011101100010101010 H
b11100011011000 M
#1255
0#
0.
#1260
1#
1.
b10 +
b10 L
b111000110110001000101010 H
b11100101110001 M
#1265
0#
0.
#1270
1#
1.
b11 +
b11 L
b111001011100010010001010 H
b11100110010111 M
#1275
0#
0.
#1280
1#
1.
b100 +
b100 L
b111001100101110100100010 H
b11100110100000 M
#1285
0#
0.
#1290
1#
1.
b101 +
b101 L
b111001101000001101001000 H
b1100101101 M
#1295
0#
0.
#1300
1#
1.
b110 +
b110 L
0J
b11001011010011010010 H
1I
b11011101000001 M
#1305
0#
0.
#1310
1#
1.
b111 +
#1315
0#
0.
#1320
1#
1.
b1000 +
#1325
0#
0.
#1330
1#
1.
b1001 +
#1335
0#
0.
#1340
1#
1.
b1010 +
#1345
0#
0.
#1350
1#
1.
b1011 +
#1355
0#
0.
#1360
1#
1.
b1100 +
#1365
0#
0.
#1370
1#
1.
b1101 +
#1375
0#
0.
#1380
1#
1.
b1001 *
b11111100101 %
b1001110111 &
b100110111010101110011 )
b11111100101 '
b1001110111 (
1$
1G
1F
1E
0D
1C
1B
1A
0@
0?
1>
0=
0<
1;
0:
19
08
07
16
15
14
13
12
11
00
1/
#1385
0#
0.
#1390
1#
1.
b0 L
b11111100101 K
b1001110111 H
0I
0U
0R
0Q
0b
0_
0^
1p
1m
1l
b11100000011011 M
#1391
0$
bx %
bx &
b0 +
0/
xG
xF
xE
xD
xC
xB
xA
x@
x?
x>
x=
x<
x;
x:
x9
x8
x7
x6
x5
x4
x3
x2
x1
x0
#1395
0#
0.
#1400
1#
1.
b1 +
b1 L
1J
b111000000110110010011101 H
b110111010000 M
#1405
0#
0.
#1410
1#
1.
b10 +
b10 L
0J
b1101110100001100100111 H
b11101110001111 M
#1415
0#
0.
#1420
1#
1.
b11 +
b11 L
1J
b111011100011110011001001 H
b111010101101 M
#1425
0#
0.
#1430
1#
1.
b100 +
b100 L
0J
b1110101011011100110010 H
b11001111100001 M
#1435
0#
0.
#1440
1#
1.
b101 +
b101 L
1J
b110011111000010111001100 H
b10011011101 M
#1445
0#
0.
#1450
1#
1.
b110 +
b110 L
0J
b100110111010101110011 H
1I
b11100101010010 M
#1455
0#
0.
#1460
1#
1.
b111 +
#1465
0#
0.
#1470
1#
1.
b1000 +
#1475
0#
0.
#1480
1#
1.
b1001 +
#1485
0#
0.
#1490
1#
1.
b1010 +
#1495
0#
0.
#1500
1#
1.
b1011 +
#1505
0#
0.
#1510
1#
1.
b1100 +
#1515
0#
0.
#1520
1#
1.
b1101 +
#1525
0#
0.
#1530
1#
1.
b1010 *
b11000010010 %
b101110001111 &
b111001010000101000001110 )
b11000010010 '
b101110001111 (
1$
1G
1F
1E
1D
0C
0B
0A
1@
1?
1>
0=
1<
0;
1:
09
08
17
06
05
04
03
12
11
00
1/
#1535
0#
0.
#1540
1#
1.
b0 L
b11000010010 K
b101110001111 H
0I
0Z
1X
0V
1U
1T
1S
1R
0g
1e
0c
1b
1a
1`
1_
0u
1t
0s
1q
0p
0o
0n
0m
b11100111101110 M
#1541
0$
bx %
bx &
b0 +
0/
xG
xF
xE
xD
xC
xB
xA
x@
x?
x>
x=
x<
x;
x:
x9
x8
x7
x6
x5
x4
x3
x2
x1
x0
#1545
0#
0.
#1550
1#
1.
b1 +
b1 L
1J
b111001111011101011100011 H
b11111001111011 M
#1555
0#
0.
#1560
1#
1.
b10 +
b10 L
b111110011110111010111000 H
b10110110000 M
#1565
0#
0.
#1570
1#
1.
b11 +
b11 L
0J
b101101100001110101110 H
b11010101001000 M
#1575
0#
0.
#1580
1#
1.
b100 +
b100 L
1J
b110101010010000011101011 H
b11110101010010 M
#1585
0#
0.
#1590
1#
1.
b101 +
b101 L
b111101010100100000111010 H
b11100101000010 M
#1595
0#
0.
#1600
1#
1.
b110 +
b110 L
b111001010000101000001110 H
1I
b11100000111110 M
#1605
0#
0.
#1610
1#
1.
b111 +
#1615
0#
0.
#1620
1#
1.
b1000 +
#1625
0#
0.
#1630
1#
1.
b1001 +
#1635
0#
0.
#1640
1#
1.
b1010 +
#1645
0#
0.
#1650
1#
1.
b1011 +
#1655
0#
0.
#1660
1#
1.
b1100 +
#1665
0#
0.
#1670
1#
1.
b1101 +
#1675
0#
0.
#1680
1#
1.
b1011 *
b100111110010 %
b11011001110 &
b110101101100110010111100 )
b100111110010 '
b11011001110 (
1$
0G
1F
1E
1D
0C
0B
1A
1@
0?
1>
1=
0<
0;
1:
09
08
17
16
15
14
13
02
01
10
1/
#1685
0#
0.
#1690
1#
1.
0J
b0 L
b100111110010 K
b11011001110 H
0I
0U
0T
0S
0R
1Q
1P
0O
0N
0b
0a
0`
0_
1^
1]
0\
0[
1p
1o
1n
1m
0l
0k
1j
1i
b110000011100 M
#1691
0$
bx %
bx &
b0 +
0/
xG
xF
xE
xD
xC
xB
xA
x@
x?
x>
x=
x<
x;
x:
x9
x8
x7
x6
x5
x4
x3
x2
x1
x0
#1695
0#
0.
#1700
1#
1.
b1 +
b1 L
1J
b1100000111000110110011 H
b1100000111 M
#1705
0#
0.
#1710
1#
1.
b10 +
b10 L
b11000001110001101100 H
b11101010110011 M
#1715
0#
0.
#1720
1#
1.
b11 +
b11 L
0J
b111010101100111100011011 H
b10010111010 M
#1725
0#
0.
#1730
1#
1.
b100 +
b100 L
1J
b100101110101111000110 H
b11100111100 M
#1735
0#
0.
#1740
1#
1.
b101 +
b101 L
b111001111001011110001 H
b11010110110011 M
#1745
0#
0.
#1750
1#
1.
b110 +
b110 L
0J
b110101101100110010111100 H
1I
b11110101101100 M
#1755
0#
0.
#1760
1#
1.
b111 +
#1765
0#
0.
#1770
1#
1.
b1000 +
#1775
0#
0.
#1780
1#
1.
b1001 +
#1785
0#
0.
#1790
1#
1.
b1010 +
#1795
0#
0.
#1800
1#
1.
b1011 +
#1805
0#
0.
#1810
1#
1.
b1100 +
#1815
0#
0.
#1820
1#
1.
b1101 +
#1825
0#
0.
#1830
1#
1.
b1100 *
b101011101000 %
b111011000101 &
b1100100010010001000 )
b101011101000 '
b111011000101 (
1$
1G
0F
1E
0D
0C
0B
1A
1@
0?
1>
1=
1<
0;
0:
09
18
07
16
15
14
03
12
01
10
1/
#1835
0#
0.
#1840
1#
1.
b0 L
b101011101000 K
b111011000101 H
0I
0Y
0X
1V
1R
0Q
0f
0e
1c
1_
0^
0t
1r
0q
0m
1l
b11101011101000 M
#1841
0$
bx %
bx &
b0 +
0/
xG
xF
xE
xD
xC
xB
xA
x@
x?
x>
x=
x<
x;
x:
x9
x8
x7
x6
x5
x4
x3
x2
x1
x0
#1845
0#
0.
#1850
1#
1.
b1 +
b1 L
b111010111010001110110001 H
b11100110100010 M
#1855
0#
0.
#1860
1#
1.
b10 +
b10 L
b111001101000100011101100 H
b11111001101000 M
#1865
0#
0.
#1870
1#
1.
b11 +
b11 L
b111110011010001000111011 H
b10010110010 M
#1875
0#
0.
#1880
1#
1.
b100 +
b100 L
1J
b100101100100010001110 H
b11001000100 M
#1885
0#
0.
#1890
1#
1.
b101 +
b101 L
b110010001001000100011 H
b110010001 M
